poultry/__init__.py
poultry/config.py
poultry/consumers.py
poultry/main.py
poultry/merge.py
poultry/options.py
poultry/producers.py
poultry/stream.py
poultry/tweet.py
poultry/utils.py
poultry-1.5.2.dist-info/LICENSE
poultry-1.5.2.dist-info/METADATA
poultry-1.5.2.dist-info/WHEEL
poultry-1.5.2.dist-info/entry_points.txt
poultry-1.5.2.dist-info/top_level.txt
poultry-1.5.2.dist-info/RECORD
