Metadata-Version: 2.1
Name: poultry
Version: 1.5.2
Summary: A tweet collection manager.
Home-page: https://github.com/dimazest/poultry
Author: Dmitrijs Milajevs
Author-email: dimazest@gmail.com
License: MIT license
Platform: UNKNOWN
Classifier: Development Status :: 3 - Alpha
Classifier: Intended Audience :: Developers
Classifier: Intended Audience :: Science/Research
Classifier: License :: OSI Approved :: MIT License
Classifier: Operating System :: POSIX
Classifier: Operating System :: Microsoft :: Windows
Classifier: Operating System :: MacOS :: MacOS X
Classifier: Topic :: Utilities
Classifier: Programming Language :: Python :: 3
Requires-Dist: opster
Requires-Dist: setuptools
Requires-Dist: requests
Requires-Dist: requests-oauthlib
